filmsdk/__init__.py
filmsdk/film_client.py
filmsdk/film_config.py
filmsdk/schemas/__init__.py
filmsdk/schemas/schemas.py
filmsdk_gadeumarcy-0.0.4.dist-info/METADATA
filmsdk_gadeumarcy-0.0.4.dist-info/WHEEL
filmsdk_gadeumarcy-0.0.4.dist-info/top_level.txt
filmsdk_gadeumarcy-0.0.4.dist-info/RECORD
