Metadata-Version: 2.4
Name: filmsdk_gadeumarcy
Version: 0.0.4
Summary: SDK Python pour accéder à l’API MovieLens (Data Analysts/Data Scientists friendly)
Author: [GADEU MONTHE VINETTE MARCY]
Classifier: Development Status :: 3 - Alpha
Classifier: Programming Language :: Python :: 3
Classifier: License :: OSI Approved :: MIT License
Classifier: Operating System :: OS Independent
Requires-Python: >=3.10
Requires-Dist: httpx>=0.28.1
Requires-Dist: pydantic>=2.11.3
Requires-Dist: backoff>=2.2.1
Requires-Dist: numpy>=2.2.4
Requires-Dist: pandas>=2.2.3
Requires-Dist: python-dotenv
